topsis_himayat/__init__.py
topsis_himayat/main.py
topsis_himayat_102313049-1.0.0.dist-info/licenses/LICENSE
topsis_himayat_102313049-1.0.0.dist-info/METADATA
topsis_himayat_102313049-1.0.0.dist-info/WHEEL
topsis_himayat_102313049-1.0.0.dist-info/entry_points.txt
topsis_himayat_102313049-1.0.0.dist-info/top_level.txt
topsis_himayat_102313049-1.0.0.dist-info/RECORD
