Metadata-Version: 2.4
Name: Topsis-Himayat-102313049
Version: 1.0.0
Summary: TOPSIS Command Line Tool
Author: Himayat
Author-email: htiwana_be23@thapar.edu
License-File: LICENSE
Requires-Dist: pandas
Requires-Dist: numpy
Dynamic: author
Dynamic: author-email
Dynamic: license-file
Dynamic: requires-dist
Dynamic: summary
